typed_format_version/__init__.py
typed_format_version/py.typed
typed_format_version-0.2.2.dist-info/METADATA
typed_format_version-0.2.2.dist-info/WHEEL
typed_format_version-0.2.2.dist-info/RECORD
