Metadata-Version: 2.4
Name: typed-format-version
Version: 0.2.2
Summary: Extract the version of a structured file's format specification.
Project-URL: Homepage, https://devel.ringlet.net/devel/typed-format-version/
Project-URL: Source, https://gitlab.com/ppentchev/typed-format-version
Project-URL: API Reference, https://devel.ringlet.net/devel/typed-format-version/api-python/
Author-email: Peter Pentchev <roam@ringlet.net>
Classifier: Development Status :: 5 - Production/Stable
Classifier: Intended Audience :: Developers
Classifier: License :: DFSG approved
Classifier: License :: Freely Distributable
Classifier: License :: OSI Approved :: BSD License
Classifier: Operating System :: OS Independent
Classifier: Programming Language :: Python
Classifier: Programming Language :: Python :: 3
Classifier: Programming Language :: Python :: 3.8
Classifier: Programming Language :: Python :: 3.9
Classifier: Programming Language :: Python :: 3.10
Classifier: Programming Language :: Python :: 3.11
Classifier: Programming Language :: Python :: 3.12
Classifier: Programming Language :: Python :: 3.13
Classifier: Topic :: Software Development :: Libraries
Classifier: Topic :: Software Development :: Libraries :: Python Modules
Classifier: Typing :: Typed
Requires-Python: >=3.8
Requires-Dist: typedload<3,>=2
